README.rst
setup.py
src/thot/__init__.py
src/thot/app.py
src/thot/core.py
src/thot/parser.py
src/thot/template.py
src/thot/url.py
src/thot/utils.py
src/thot.egg-info/PKG-INFO
src/thot.egg-info/SOURCES.txt
src/thot.egg-info/dependency_links.txt
src/thot.egg-info/entry_points.txt
src/thot.egg-info/not-zip-safe
src/thot.egg-info/requires.txt
src/thot.egg-info/top_level.txt
src/thot/plugins/Comments.py
src/thot/plugins/CreoleParser.py
src/thot/plugins/HtmlPostProcessing.py
src/thot/plugins/Jinja2Templating.py
src/thot/plugins/MakoTemplating.py
src/thot/plugins/MarkdownParser.py
src/thot/plugins/RstParser.py
src/thot/plugins/Tagging.py
src/thot/plugins/TracParser.py
src/thot/plugins/__init__.py