Metadata-Version: 1.1
Name: thot
Version: 1.1.0
Summary: A Python-Powered Static Site Generator
Home-page: http://github.com/wmark/thot
Author: W-Mark Kubacki, Arthur Koziel
Author-email: wmark+thot@hurrikane.de
License: http://www.opensource.org/licenses/rpl1.5
Download-URL: http://github.com/downloads/wmark/thot/thot-1.1.0.tar.gz
Platform: UNKNOWN
